odoo9_addon_l10n_de_country_states-9.0.1.0.0-py2.7-nspkg.pth
odoo9_addon_l10n_de_country_states-9.0.1.0.0.dist-info/DESCRIPTION.rst
odoo9_addon_l10n_de_country_states-9.0.1.0.0.dist-info/METADATA
odoo9_addon_l10n_de_country_states-9.0.1.0.0.dist-info/RECORD
odoo9_addon_l10n_de_country_states-9.0.1.0.0.dist-info/WHEEL
odoo9_addon_l10n_de_country_states-9.0.1.0.0.dist-info/metadata.json
odoo9_addon_l10n_de_country_states-9.0.1.0.0.dist-info/namespace_packages.txt
odoo9_addon_l10n_de_country_states-9.0.1.0.0.dist-info/top_level.txt
odoo_addons/l10n_de_country_states/README.rst
odoo_addons/l10n_de_country_states/__init__.py
odoo_addons/l10n_de_country_states/__openerp__.py
odoo_addons/l10n_de_country_states/data/res_country_states.xml
odoo_addons/l10n_de_country_states/i18n/de.po
